ukrainian/__init__.py
ukrainian-0.0.3.dist-info/LICENSE
ukrainian-0.0.3.dist-info/METADATA
ukrainian-0.0.3.dist-info/WHEEL
ukrainian-0.0.3.dist-info/top_level.txt
ukrainian-0.0.3.dist-info/RECORD
