Metadata-Version: 2.1
Name: ukrainian
Version: 0.0.3
Summary: Manipulate Ukrainain words and letters.
Home-page: https://github.com/bellemanwesley/ukrainian
Author: Wesley Belleman
Author-email: bellemanwesley@gmail.com
License: MIT
Platform: UNKNOWN
Classifier: Programming Language :: Python :: 3
Classifier: License :: OSI Approved :: MIT License
Classifier: Operating System :: OS Independent
Requires-Python: >=3.6
